fusekit/__init__.py
fusekit/core.py
fusekit/Common/Batching.py
fusekit/Common/EvalType.py
fusekit/Common/Memory.py
fusekit/Common/__init__.py
fusekit/Common/env.py
fusekit/Common/multithread.py
fusekit/Common/utils.py
fusekit/Datasets/__init__.py
fusekit/Datasets/base.py
fusekit/Datasets/core.py
fusekit/Datasets/extensions.py
fusekit/Datasets/BBH/BBH.py
fusekit/Datasets/CommonsenseQA/CommonsenseQA.py
fusekit/Datasets/CommonsenseQA/dev_rand_split.jsonl
fusekit/Datasets/CommonsenseQA/test_rand_split_no_answers.jsonl
fusekit/Datasets/CommonsenseQA/train_rand_split.jsonl
fusekit/Datasets/MMLU/MMLU.py
fusekit/Modeling/__init__.py
fusekit/Modeling/api_model.py
fusekit/Modeling/base.py
fusekit/Modeling/causal_model.py
fusekit/Modeling/chatGPT.py
fusekit/Modeling/claude.py
fusekit/Modeling/composition.py
fusekit/Modeling/gemini.py
fusekit/Modeling/llama2.py
fusekit/Modeling/llama3.py
fusekit/Modeling/llava_next.py
fusekit/Modeling/model_hooks.py
fusekit/Modeling/phi3.py
fusekit/Modeling/pixtral.py
fusekit/Modeling/qwen2.py
fusekit/Modeling/training.py
fusekit-0.1.0a2.dist-info/METADATA
fusekit-0.1.0a2.dist-info/WHEEL
fusekit-0.1.0a2.dist-info/entry_points.txt
fusekit-0.1.0a2.dist-info/RECORD
