Metadata-Version: 2.4
Name: fusekit
Version: 0.1.0a2
Summary: Composable inference & GPU fusion engine (HF + PEFT).
Author-email: Christian Arnold <cmarnold@mit.edu>, Andrew Alini <andrew.alini@ll.mit.edu>
License: Apache-2.0
Requires-Python: >=3.11
Requires-Dist: accelerate>=1.10.1
Requires-Dist: anthropic>=0.72.0
Requires-Dist: click>=8.3.0
Requires-Dist: datasets>=4.0.0
Requires-Dist: google-genai>=1.43.0
Requires-Dist: numpy>=2.3.4
Requires-Dist: openai>=2.6.1
Requires-Dist: pandas>=2.3.3
Requires-Dist: peft>=0.17.1
Requires-Dist: pillow>=12.0.0
Requires-Dist: protobuf>=3.20.3
Requires-Dist: pymupdf>=1.25.5
Requires-Dist: requests>=2.32.5
Requires-Dist: sentencepiece>=0.2.1
Requires-Dist: torch>=2.6.0
Requires-Dist: tqdm>=4.67.1
Requires-Dist: transformers==4.51.3
